usb_plug_notification_linux.py
usb_plug_notification_linux-0.1.3.dist-info/METADATA
usb_plug_notification_linux-0.1.3.dist-info/WHEEL
usb_plug_notification_linux-0.1.3.dist-info/entry_points.txt
usb_plug_notification_linux-0.1.3.dist-info/RECORD
