Metadata-Version: 2.1
Name: usb-plug-notification-linux
Version: 0.1.3
Summary: Python script to get plug/unplug events on Linux
License: GPL-3.0
Author: Dick Marinus
Requires-Python: >=3.9,<4
Classifier: License :: OSI Approved :: GNU General Public License v3 (GPLv3)
Classifier: Programming Language :: Python :: 3
Classifier: Programming Language :: Python :: 3.9
Classifier: Programming Language :: Python :: 3.10
Classifier: Programming Language :: Python :: 3.11
Classifier: Programming Language :: Python :: 3.12
Requires-Dist: click (>=8.0.1,<9.0.0)
Requires-Dist: pyudev (>=0.6.0)
